c81utils.py
c81utils-1.0.7.dist-info/LICENSE
c81utils-1.0.7.dist-info/METADATA
c81utils-1.0.7.dist-info/WHEEL
c81utils-1.0.7.dist-info/top_level.txt
c81utils-1.0.7.dist-info/zip-safe
c81utils-1.0.7.dist-info/RECORD
