Metadata-Version: 2.1
Name: c81utils
Version: 1.0.7
Summary: Library for working with C81 airfoil data
Home-page: http://pypi.python.org/pypi/c81utils
Author: Cibin Joseph
Author-email: cibinjoseph92@gmail.com
License: GPL3
Keywords: c81
Platform: UNKNOWN
Classifier: Development Status :: 5 - Production/Stable
Classifier: Intended Audience :: Science/Research
Classifier: Operating System :: OS Independent
Classifier: License :: OSI Approved :: GNU General Public License v3 or later (GPLv3+)
Classifier: Programming Language :: Python :: 3
Classifier: Topic :: Scientific/Engineering
Requires-Python: >=3
License-File: LICENSE
Requires-Dist: numpy
Requires-Dist: scipy
